{
  "press-to-start": "Duw op een knop om te starten",
  "press-to-restart": "Duw op een knop om opnieuw te beginnen",
  "choose-num-players": "Kies het aantal spelers",
  "choose-bot-type": {
    "difficulty": "Kies de moeilijkheidsgraad van de computer",
    "strategy": "Kies de strategie van de computer"
  },
  "bot-types": {
    "difficulty": {
      "none": "Geen",
      "random": "Makkelijk",
      "random-tip": "Zoekt willekeurig zonder strategie",
      "gradient-descent": "Medium",
      "gradient-descent-tip": "Volgt de neerwaartse helling van de sondes naar de bodem",
      "tangent-intersection": "Moeilijk",
      "tangent-intersection-tip": "Gebruikt de sondes van alle spelers om te beslissen waar te zoeken"
    },
    "strategy": {
      "none": "Geen",
      "random": "Willekeurig",
      "gradient-descent": "Gradient descent",
      "tangent-intersection": "Raaklijnenmethode"
    }
  },
  "remaining-time": "Tijd:",
  "remaining-probes": "Pogingen:",
  "objective": "Vind de schat op het diepste punt van de oceaan!",
  "go": "Start!",
  "win-announcement-begin": "Speler ",
  "win-announcement-end": " vond de schat:",
  "time-is-up": "De tijd is om!",
  "no-probes-left": "Geen resterende pogingen!",
  "game-over": "Game over!",
  "treasures": [
    "Fermat’s Verloren Bewijs",
    "Het laatste cijfer van Pi",
    "De laatste priemtweeling",
    "Een perpetuum mobile",
    "Instructies voor de kwadratuur van de cirkel",
    "Pythagoras’ gitaarplectrum",
    "Newton's appeltaart recept",
    "De badeend van Archimedes",
    "Hilbert's hotelkamersleutel",
    "Zeno's boog (de pijl vliegt nog ergens rond)",
    "Een Rubik hyperkubus",
    "Het verschil tussen 0,999... en 1",
    "Een verbeterde 0, die kan worden gedeeld door 0",
    "Een boek met alle mogelijke Sudoku's",
    "Een lidmaatschapskaart voor de Oneindige Bibliotheek",
    "De zesde platonische lichaam",
    "Een kwantummunt die aan beide kanten tegelijk landt",
    "Een oneindige reeks Matroesjka poppen",
    "Een mooiere verhouding dan de gulden snede",
    "Schrödingers doos (kat niet inbegrepen)",
    "Ada Lovelace's verloren coderingstutorial"
  ],
  "demo-explanation": [
    [
      "In het diepste gedeelte van de zeebodem ligt een schat.",
      "Werp sondes vanaf je schip op verschillende plaatsen om hem te vinden."
    ],
    ["Wat is je beste strategie?"],
    [
      "Neurale netwerken leren door een vergelijkbare strategie te gebruiken.",
      "Ze volgen hun eerdere pogingen en komen steeds dichter bij de beste oplossing."
    ]
  ]
}
